pybuilder_cram_console_scripts/__init__.py
pybuilder_cram_console_scripts/utils.py
pybuilder_cram_console_scripts-1.0.4.dist-info/DESCRIPTION.rst
pybuilder_cram_console_scripts-1.0.4.dist-info/METADATA
pybuilder_cram_console_scripts-1.0.4.dist-info/RECORD
pybuilder_cram_console_scripts-1.0.4.dist-info/WHEEL
pybuilder_cram_console_scripts-1.0.4.dist-info/metadata.json
pybuilder_cram_console_scripts-1.0.4.dist-info/namespace_packages.txt
pybuilder_cram_console_scripts-1.0.4.dist-info/top_level.txt
pybuilder_cram_console_scripts-1.0.4.dist-info/zip-safe
