Metadata-Version: 2.0
Name: pybuilder-cram-console-scripts
Version: 1.0.4
Summary: PyBuilder Cram Console Scripts Plugin
Home-page: https://github.com/AlexeySanko/pybuilder_cram_console_scripts
Author: Alexey Sanko
Author-email: alexeycount@gmail.com
License: Apache License, Version 2.0
Platform: UNKNOWN
Classifier: Development Status :: 4 - Beta
Classifier: Environment :: Console
Classifier: Intended Audience :: Developers
Classifier: License :: OSI Approved :: Apache Software License
Classifier: Programming Language :: Python
Classifier: Programming Language :: Python :: 2
Classifier: Programming Language :: Python :: 2.7
Classifier: Programming Language :: Python :: 3
Classifier: Programming Language :: Python :: 3.2
Classifier: Programming Language :: Python :: 3.3
Classifier: Programming Language :: Python :: 3.4
Classifier: Programming Language :: Python :: 3.5
